pymta/__init__.py
pymta/api.py
pymta/command_parser.py
pymta/compat.py
pymta/exceptions.py
pymta/model.py
pymta/mta.py
pymta/session.py
pymta/statemachine.py
pymta/test_util.py
pymta/validation.py
pymta-0.8.0.dist-info/COPYING.txt
pymta-0.8.0.dist-info/METADATA
pymta-0.8.0.dist-info/WHEEL
pymta-0.8.0.dist-info/top_level.txt
pymta-0.8.0.dist-info/RECORD
