Metadata-Version: 2.1
Name: pymta
Version: 0.8.0
Summary: library to build a custom SMTP server
Home-page: https://github.com/FelixSchwarz/pymta
Author: Felix Schwarz
Author-email: felix.schwarz@oss.schwarz.eu
License: MIT
Project-URL: Code, https://github.com/FelixSchwarz/pymta
Project-URL: Issue tracker, https://github.com/FelixSchwarz/pymta/issues
Classifier: Development Status :: 4 - Beta
Classifier: Intended Audience :: Developers
Classifier: License :: OSI Approved :: MIT License
Classifier: Operating System :: OS Independent
Classifier: Programming Language :: Python
Classifier: Topic :: Communications :: Email
Classifier: Topic :: Software Development :: Libraries :: Python Modules
Requires-Python: !=3.0.*,!=3.1.*,!=3.2.*,!=3.3.*,>=2.7
License-File: COPYING.txt
Requires-Dist: pycerberus >=0.5
Provides-Extra: testing
Requires-Dist: pytest ; extra == 'testing'
Requires-Dist: dotmap <=1.3.24 ; (python_version < "3.0") and extra == 'testing'
Requires-Dist: dotmap ; (python_version >= "3.0") and extra == 'testing'
